IEXTools/IEXDownloader.py
IEXTools/IEXHISTExceptions.py
IEXTools/IEX_API.py
IEXTools/IEXparser.py
IEXTools/TypeAliases.py
IEXTools/__init__.py
IEXTools/benchmarking.py
IEXTools/messages.py
IEXTools/test_1.5.py
IEXTools/tests/__init__.py
IEXTools/tests/test_api.py
IEXTools/tests/test_parser.py
IEXTools-0.0.8.dist-info/LICENSE
IEXTools-0.0.8.dist-info/METADATA
IEXTools-0.0.8.dist-info/WHEEL
IEXTools-0.0.8.dist-info/top_level.txt
IEXTools-0.0.8.dist-info/RECORD
