Metadata-Version: 2.1
Name: IEXTools
Version: 0.0.8
Summary: ('Package for handling IEX stock market data',)
Home-page: https://github.com/vfrazao-ns1/IEXTools
Author: Victor Frazao
Author-email: 
License: Apache 2.0
Platform: UNKNOWN
Classifier: License :: OSI Approved :: Apache Software License
Classifier: Programming Language :: Python
Classifier: Programming Language :: Python :: 3
Classifier: Programming Language :: Python :: 3.7
Classifier: Programming Language :: Python :: Implementation :: CPython
Requires-Python: >=3.7.0
Requires-Dist: requests
